raxit/__init__.py
raxit/raxit.abi3.so
raxit_sdk-0.1.2.dist-info/METADATA
raxit_sdk-0.1.2.dist-info/WHEEL
raxit_sdk-0.1.2.dist-info/RECORD
