Metadata-Version: 2.4
Name: raxit-sdk
Version: 0.1.2
Classifier: Development Status :: 4 - Beta
Classifier: Intended Audience :: Developers
Classifier: License :: OSI Approved :: MIT License
Classifier: License :: OSI Approved :: Apache Software License
Classifier: Programming Language :: Rust
Classifier: Programming Language :: Python :: 3
Classifier: Programming Language :: Python :: 3.8
Classifier: Programming Language :: Python :: 3.9
Classifier: Programming Language :: Python :: 3.10
Classifier: Programming Language :: Python :: 3.11
Classifier: Programming Language :: Python :: 3.12
Classifier: Programming Language :: Python :: 3.13
Classifier: Topic :: Software Development :: Libraries
Classifier: Topic :: Security
Summary: RAXIT SDK - Runtime AI eXecution Integrity & Trust
Keywords: security,ai,agents,static-analysis,trust
Home-Page: https://github.com/raxitlabs/ai-security
Author-email: RAXIT Labs <info@raxitlabs.com>
License: MIT OR Apache-2.0
Requires-Python: >=3.8
Project-URL: Documentation, https://github.com/raxitlabs/ai-security/tree/main/src/ai-security-sdk
Project-URL: Homepage, https://github.com/raxitlabs/ai-security
Project-URL: Repository, https://github.com/raxitlabs/ai-security
